README
setup.py
pyramid_redis_token_authentication/__init__.py
pyramid_redis_token_authentication/_impl.py
pyramid_redis_token_authentication.egg-info/PKG-INFO
pyramid_redis_token_authentication.egg-info/SOURCES.txt
pyramid_redis_token_authentication.egg-info/dependency_links.txt
pyramid_redis_token_authentication.egg-info/requires.txt
pyramid_redis_token_authentication.egg-info/top_level.txt