Metadata-Version: 1.1
Name: pyramid-redis-token-authentication
Version: 0.2
Summary: Authentication policy for Pyramid which stores counterfoils of tokens in Redis
Home-page: https://github.com/sherwoodwang/pyramid-redis-token-authentication
Author: Sherwood Wang
Author-email: sherwood@wang.onl
License: UNKNOWN
Platform: UNKNOWN
Classifier: Programming Language :: Python
Classifier: Framework :: Pyramid
Classifier: Topic :: Internet :: WWW/HTTP
